hytra/__init__.py
hytra/hypergraph.py
hytra/transversal_tests.py
hytra/transversals.py
HyTra-0.0.3a1.dist-info/LICENSE
HyTra-0.0.3a1.dist-info/METADATA
HyTra-0.0.3a1.dist-info/WHEEL
HyTra-0.0.3a1.dist-info/top_level.txt
HyTra-0.0.3a1.dist-info/RECORD
