Metadata-Version: 2.1
Name: HyTra
Version: 0.0.3a1
Summary: Hypergraph Transversals
Home-page: https://github.com/balqui/HyTra
Author: José Luis Balcázar
Author-email: joseluisbalcazar@gmail.com
License: UNKNOWN
Platform: UNKNOWN
Classifier: Programming Language :: Python :: 3
Classifier: License :: OSI Approved :: MIT License
Classifier: Operating System :: OS Independent
Classifier: Development Status :: 3 - Alpha
Classifier: Topic :: Scientific/Engineering :: Mathematics
Requires-Python: >=2.7
